CHANGES.rst
LICENSE
MANIFEST.in
README.rst
setup.py
django_vimeo/__init__.py
django_vimeo/cache.py
django_vimeo/exceptions.py
django_vimeo/fields.py
django_vimeo/storage.py
django_vimeo.egg-info/PKG-INFO
django_vimeo.egg-info/SOURCES.txt
django_vimeo.egg-info/dependency_links.txt
django_vimeo.egg-info/requires.txt
django_vimeo.egg-info/top_level.txt
django_vimeo/templatetags/__init__.py
django_vimeo/templatetags/django_vimeo_tags.py