Metadata-Version: 1.1
Name: django-vimeo
Version: 0.1.8
Summary: Django app for easy embeding Vimeo videos.
Home-page: https://github.com/suquant/django-vimeo
Author: Georgy Kutsurua
Author-email: g.kutsurua@gmail.com
License: UNKNOWN
Keywords: vimeo,video
Platform: UNKNOWN
Classifier: Framework :: Django
Classifier: License :: OSI Approved :: MIT License
Classifier: Programming Language :: Python
Classifier: Programming Language :: Python :: 3
Classifier: Programming Language :: Python :: 2.7
Classifier: Topic :: Internet :: WWW/HTTP
